{
  "package_name": "hyper",
  "display_name": "Hyper",
  "aliases": [
    "hyper"
  ],
  "exec_name": "Hyper",
  "portable": false,
  "creator": "HyperTerminal",
  "description": "A terminal built on web technologies.",
  "latest_version": "3.4.1",
  "threads": 8,
  "iswitches": [
    "/S"
  ],
  "uswitches": [],
  "autoupdate": {
    "download_page": "https://github.com/vercel/hyper/releases/latest",
    "download_url": "https://github.com/vercel/hyper/releases/download/v<version>/Hyper-Setup-<version>.exe",
    "regex": "<title>Release (\\d+\\.\\d+\\.\\d+) · vercel/hyper"
  },
  "3.4.1": {
    "url": "\t\n\nhttps://github.com/vercel/hyper/releases/download/v3.4.1/Hyper-Setup-3.4.1.exe",
    "size": 0,
    "checksum": "0",
    "file_type": ".exe"
  }
}